MANIFEST.in
README.md
pypi_desc.md
setup.cfg
setup.py
GeneralNewsExtractor.egg-info/PKG-INFO
GeneralNewsExtractor.egg-info/SOURCES.txt
GeneralNewsExtractor.egg-info/dependency_links.txt
GeneralNewsExtractor.egg-info/requires.txt
GeneralNewsExtractor.egg-info/top_level.txt
gne/__init__.py
gne/defaults.py
gne/utils.py
gne/extractor/AuthorExtractor.py
gne/extractor/ContentExtractor.py
gne/extractor/TimeExtractor.py
gne/extractor/TitleExtractor.py
gne/extractor/__init__.py